LICENSE
README.md
chaosape.py
example.py
pyproject.toml
setup.cfg
chaosape-2025.2.19.post5.data/data/bin/LICENSE
chaosape-2025.2.19.post5.data/data/bin/chaosape.py
chaosape.egg-info/PKG-INFO
chaosape.egg-info/SOURCES.txt
chaosape.egg-info/dependency_links.txt
chaosape.egg-info/top_level.txt
chaosape-2025.2.19.post5.dist-info/LICENSE
chaosape-2025.2.19.post5.dist-info/METADATA
chaosape-2025.2.19.post5.dist-info/WHEEL
chaosape-2025.2.19.post5.dist-info/top_level.txt
chaosape-2025.2.19.post5.dist-info/RECORD
