Metadata-Version: 2.2
Name: chaosape
Version: 2025.2.19.post5
Summary: A tool for testing what happens if base functions of python except
Home-page: https://github.com/NormanTUD/ChaosApe/
Author: Norman Koch
Author-email: norman.koch@tu-dresden.de
Platform: Linux
License-File: LICENSE
Dynamic: home-page
Dynamic: platform
